dagster_ncsa/__init__.py
dagster_ncsa/_version.py
dagster_ncsa/airtable_catalog_resource.py
dagster_ncsa/models.py
dagster_ncsa/py.typed
dagster_ncsa/redcap_dagster_resource.py
dagster_ncsa/s3_resource_ncsa.py
dagster_ncsa-0.2.0.dist-info/METADATA
dagster_ncsa-0.2.0.dist-info/WHEEL
dagster_ncsa-0.2.0.dist-info/licenses/LICENSE
dagster_ncsa-0.2.0.dist-info/RECORD
